deferpy/__init__.py
deferpy/defer.py
tests/__init__.py
tests/test_defer.py
deferpy-1.0.1.dist-info/METADATA
deferpy-1.0.1.dist-info/WHEEL
deferpy-1.0.1.dist-info/top_level.txt
deferpy-1.0.1.dist-info/RECORD
