Metadata-Version: 2.1
Name: deferpy
Version: 1.0.1
Summary: UNKNOWN
Home-page: UNKNOWN
Author: David Buckley <david@davidbuckley.ca>
License: UNKNOWN
Platform: UNKNOWN
Requires-Dist: wrapt
Provides-Extra: dev
Requires-Dist: pytest ; extra == 'dev'
